{
  "authors": [
    "discord:503909141253849118"
  ],
  "contents": [
    {
      "description": "Moderation, Memes and many more!",
      "locale": "en-GB",
      "name": "IzTheKing",
      "page": "This is a hopefully cool Discord Bot! \r\nWith moderation memes, Utility, and Games! \r\nFor commands type: !help \r\nyou want suggesting something for my Bot? \r\n!suggest <Your Suggestion> \r\n  When you need help with something? \r\n  !discord and join our Support Server! \r\n  I'm not everytime online but please be patient with waiting! \r\n  Thanks for adding my Bot! \r\n  Have a great Day!"
    }
  ],
  "created": 1567535592842,
  "edited": 1567883492184,
  "flags": {
    "adverts": false,
    "inAppPurchases": false
  },
  "hide": false,
  "id": "583559430738542592",
  "images": {
    "avatar": null,
    "cover": null,
    "preview": []
  },
  "invite": {
    "discord": "https://discordapp.com/api/oauth2/authorize?client_id=583559430738542592&permissions=8&scope=bot"
  },
  "nsfw": false,
  "state": "approved",
  "support": "https://discord.gg/envZFf7",
  "trigger": {
    "customisable": false,
    "mentionable": false,
    "prefix": [
      "!"
    ]
  },
  "videos": {
    "youku": null,
    "youtube": null
  },
  "website": null,
  "source": null,
  "categories": [
    "utility"
  ]
}
